setup.py
phoenix_ml7/Framework.py
phoenix_ml7/__init__.py
phoenix_ml7.egg-info/PKG-INFO
phoenix_ml7.egg-info/SOURCES.txt
phoenix_ml7.egg-info/dependency_links.txt
phoenix_ml7.egg-info/not-zip-safe
phoenix_ml7.egg-info/top_level.txt